ithaca/__init__.py
ithaca/analytics.py
ithaca/auth.py
ithaca/calc_server.py
ithaca/calculation.py
ithaca/chains/__init__.py
ithaca/chains/solana.py
ithaca/chains/sui.py
ithaca/client.py
ithaca/constants.py
ithaca/fundlock.py
ithaca/logger.py
ithaca/market.py
ithaca/orders.py
ithaca/protocol.py
ithaca/socket.py
ithaca_py-0.4.0.dist-info/METADATA
ithaca_py-0.4.0.dist-info/WHEEL
ithaca_py-0.4.0.dist-info/RECORD
