Metadata-Version: 2.4
Name: ithaca_py
Version: 0.4.0
Summary: Ithaca Protocol SDK
Author: nhaga
Author-email: nhaga5@gmail.com
Requires-Python: >=3.10,<4.0
Classifier: Programming Language :: Python :: 3
Classifier: Programming Language :: Python :: 3.10
Classifier: Programming Language :: Python :: 3.11
Classifier: Programming Language :: Python :: 3.12
Classifier: Programming Language :: Python :: 3.13
Classifier: Programming Language :: Python :: 3.14
Provides-Extra: docs
Requires-Dist: base58 (==2.1.1)
Requires-Dist: bech32 (==1.2.0)
Requires-Dist: cryptography (>=42.0.5,<43.0.0)
Requires-Dist: eth-account (>=0.13.1,<0.14.0)
Requires-Dist: mkdocs (>=1.6.1,<2.0.0)
Requires-Dist: mkdocs-material (>=9.6.1,<10.0.0)
Requires-Dist: pandas (>=2.1.4,<3.0.0)
Requires-Dist: pre-commit (>=3.6.0,<4.0.0)
Requires-Dist: pydantic (>=2.5.3,<3.0.0)
Requires-Dist: pydoc-markdown (>=4.8.2,<5.0.0)
Requires-Dist: pynacl (==1.6.0)
Requires-Dist: requests (>=2.32.0,<3.0.0)
Requires-Dist: scipy (>=1.11.4,<2.0.0)
Requires-Dist: solders (==0.26.0)
Requires-Dist: tenacity (>=8.2.3,<9.0.0)
Requires-Dist: web3 (>=7.4.0,<8.0.0)
Requires-Dist: websocket-client (>=1.7.0,<2.0.0)
